binance_sdk_margin_trading/__init__.py
binance_sdk_margin_trading/margin_trading.py
binance_sdk_margin_trading/metadata.py
binance_sdk_margin_trading/rest_api/__init__.py
binance_sdk_margin_trading/rest_api/api/__init__.py
binance_sdk_margin_trading/rest_api/api/account_api.py
binance_sdk_margin_trading/rest_api/api/borrow_repay_api.py
binance_sdk_margin_trading/rest_api/api/market_data_api.py
binance_sdk_margin_trading/rest_api/api/risk_data_stream_api.py
binance_sdk_margin_trading/rest_api/api/trade_api.py
binance_sdk_margin_trading/rest_api/api/transfer_api.py
binance_sdk_margin_trading/rest_api/models/__init__.py
binance_sdk_margin_trading/rest_api/models/adjust_cross_margin_max_leverage_response.py
binance_sdk_margin_trading/rest_api/models/create_special_key_response.py
binance_sdk_margin_trading/rest_api/models/cross_margin_collateral_ratio_response.py
binance_sdk_margin_trading/rest_api/models/cross_margin_collateral_ratio_response_inner.py
binance_sdk_margin_trading/rest_api/models/cross_margin_collateral_ratio_response_inner_collaterals_inner.py
binance_sdk_margin_trading/rest_api/models/disable_isolated_margin_account_response.py
binance_sdk_margin_trading/rest_api/models/enable_isolated_margin_account_response.py
binance_sdk_margin_trading/rest_api/models/enums.py
binance_sdk_margin_trading/rest_api/models/get_all_cross_margin_pairs_response.py
binance_sdk_margin_trading/rest_api/models/get_all_cross_margin_pairs_response_inner.py
binance_sdk_margin_trading/rest_api/models/get_all_isolated_margin_symbol_response.py
binance_sdk_margin_trading/rest_api/models/get_all_isolated_margin_symbol_response_inner.py
binance_sdk_margin_trading/rest_api/models/get_all_margin_assets_response.py
binance_sdk_margin_trading/rest_api/models/get_all_margin_assets_response_inner.py
binance_sdk_margin_trading/rest_api/models/get_bnb_burn_status_response.py
binance_sdk_margin_trading/rest_api/models/get_cross_margin_transfer_history_response.py
binance_sdk_margin_trading-4.3.0.dist-info/METADATA
binance_sdk_margin_trading-4.3.0.dist-info/WHEEL
binance_sdk_margin_trading-4.3.0.dist-info/licenses/LICENCE
binance_sdk_margin_trading-4.3.0.dist-info/RECORD
